README.rst
setup.py
datacoco_batch/__init__.py
datacoco_batch/batch.py
datacoco_batch.egg-info/PKG-INFO
datacoco_batch.egg-info/SOURCES.txt
datacoco_batch.egg-info/dependency_links.txt
datacoco_batch.egg-info/requires.txt
datacoco_batch.egg-info/top_level.txt