Metadata-Version: 1.0
Name: datacoco-batch
Version: 0.1.0
Summary: Data common code for batch workflows by Equinox
Home-page: https://github.com/equinoxfitness/datacoco-batch
Author: Equinox
Author-email: UNKNOWN
License: MIT
Keywords: helper,config,logging,common
Platform: UNKNOWN
